biggerquery/__init__.py
biggerquery/beam_manager.py
biggerquery/configuration.py
biggerquery/dataset_manager.py
biggerquery/deployment.py
biggerquery/gcp_defaults.py
biggerquery/interactive.py
biggerquery/job.py
biggerquery/monitoring.py
biggerquery/test_utils.py
biggerquery/utils.py
biggerquery/workflow.py
biggerquery/user_commons/__init__.py
biggerquery/user_commons/labels.py
biggerquery/user_commons/sensor.py
biggerquery/user_commons/fastai/__init__.py
biggerquery/user_commons/fastai/predict.py
biggerquery/user_commons/fastai/predict_component.py
biggerquery/user_commons/fastai/predict_io.py
biggerquery-0.6.0.data/data/requirements/base.txt
biggerquery-0.6.0.data/data/requirements/beam_extras.txt
biggerquery-0.6.0.data/data/requirements/stackdriver_extras.txt
test/test_user_commons/__init__.py
test/test_user_commons/test_labels.py
test/test_user_commons/test_sensor.py
test/test_user_commons/test_fastai/__init__.py
test/test_user_commons/test_fastai/test_predict.py
biggerquery-0.6.0.dist-info/LICENSE
biggerquery-0.6.0.dist-info/METADATA
biggerquery-0.6.0.dist-info/NOTICE
biggerquery-0.6.0.dist-info/WHEEL
biggerquery-0.6.0.dist-info/top_level.txt
biggerquery-0.6.0.dist-info/RECORD
